__main__/__init__.py
compile/__init__.py
shp/Watchdog.py
shp/__init__.py
shp/__main__.py
shp/multiShp.py
shp/shp.py
shp/__main__/__init__.py
shp/builder/Builder.py
shp/builder/BuilderStates.py
shp/builder/__init__.py
shp/compile/__init__.py
shp/compile/__main__.py
shp/compiler/Compiler.py
shp/compiler/Definition.py
shp/compiler/Dependency.py
shp/compiler/LangFuncsDefinitions.py
shp/compiler/LangFuncsManager.py
shp/compiler/RootSource.py
shp/compiler/ShpDefinitions.py
shp/compiler/Source.py
shp/compiler/__init__.py
shp/lexer/Lexer.py
shp/lexer/LexerStates.py
shp/lexer/Position.py
shp/lexer/Token.py
shp/lexer/__init__.py
shp/parser/Nodes.py
shp/parser/Parser.py
shp/parser/ParserStates.py
shp/parser/__init__.py
src/Watchdog.py
src/__init__.py
src/shp.py
shp-1.0.2.dist-info/METADATA
shp-1.0.2.dist-info/WHEEL
shp-1.0.2.dist-info/top_level.txt
shp-1.0.2.dist-info/RECORD
