Metadata-Version: 2.1
Name: shp
Version: 1.0.2
Summary: Static-Html-Preprocessor
Home-page: https://github.com/Jakub21/shp.py
Author: Jakub21
License: MIT
Platform: UNKNOWN
